LICENSE
README.md
setup.cfg
setup.py
aid_hash/__init__.py
aid_hash/algo.py
aid_hash/compat.py
aid_hash/error.py
aid_hash/icmp.py
aid_hash/icmp6.py
aid_hash.egg-info/PKG-INFO
aid_hash.egg-info/SOURCES.txt
aid_hash.egg-info/dependency_links.txt
aid_hash.egg-info/top_level.txt
scripts/all_id.py