Metadata-Version: 2.1
Name: aid-hash
Version: 1.1
Summary: All-ID flow hashing; a community_id implementation that supports timestamps
Home-page: https://github.com/stratosphereips/AID
Author: Christian Kreibich, Alya Gomaa
Author-email: christian@corelight.com, alyaggomaa@gmail.com
License: BSD
Platform: UNKNOWN
Classifier: Programming Language :: Python :: 3
Classifier: License :: OSI Approved :: BSD License
Classifier: Operating System :: OS Independent
License-File: LICENSE
